[
  {
    "Type": "Function",
    "Name": "UserConstructionScript",
    "Outer": "BP_VIPInvitation_Blank_C",
    "Class": "UScriptClass'Function'",
    "SuperStruct": {
      "ObjectName": "Function'Actor:UserConstructionScript'",
      "ObjectPath": "/Script/Engine"
    },
    "FunctionFlags": "FUNC_Event | FUNC_Public | FUNC_BlueprintCallable | FUNC_BlueprintEvent"
  },
  {
    "Type": "Function",
    "Name": "GetSensorComponent",
    "Outer": "BP_VIPInvitation_Blank_C",
    "Class": "UScriptClass'Function'",
    "Super": {
      "ObjectName": "Function'BP_KeycardBase_C:GetSensorComponent'",
      "ObjectPath": "PAYDAY3/Content/Gameplay/Props/KeycardReader/BP_KeycardBase.3"
    },
    "SuperStruct": {
      "ObjectName": "Function'BP_KeycardBase_C:GetSensorComponent'",
      "ObjectPath": "PAYDAY3/Content/Gameplay/Props/KeycardReader/BP_KeycardBase.3"
    },
    "ChildProperties": [
      {
        "Type": "ObjectProperty",
        "Name": "ReturnValue",
        "Flags": "RF_Public",
        "ElementSize": 8,
        "PropertyFlags": "Parm | OutParm | ReturnParm | InstancedReference",
        "PropertyClass": {
          "ObjectName": "Class'SBZSensorComponent'",
          "ObjectPath": "/Script/Starbreeze"
        }
      }
    ],
    "FunctionFlags": "FUNC_Event | FUNC_Public | FUNC_HasOutParms | FUNC_BlueprintCallable | FUNC_BlueprintEvent"
  },
  {
    "Type": "Function",
    "Name": "GetSensorOutlineComponent",
    "Outer": "BP_VIPInvitation_Blank_C",
    "Class": "UScriptClass'Function'",
    "Super": {
      "ObjectName": "Function'BP_KeycardBase_C:GetSensorOutlineComponent'",
      "ObjectPath": "PAYDAY3/Content/Gameplay/Props/KeycardReader/BP_KeycardBase.2"
    },
    "SuperStruct": {
      "ObjectName": "Function'BP_KeycardBase_C:GetSensorOutlineComponent'",
      "ObjectPath": "PAYDAY3/Content/Gameplay/Props/KeycardReader/BP_KeycardBase.2"
    },
    "ChildProperties": [
      {
        "Type": "ObjectProperty",
        "Name": "ReturnValue",
        "Flags": "RF_Public",
        "ElementSize": 8,
        "PropertyFlags": "Parm | OutParm | ReturnParm | InstancedReference",
        "PropertyClass": {
          "ObjectName": "Class'SBZOutlineComponent'",
          "ObjectPath": "/Script/Starbreeze"
        }
      }
    ],
    "FunctionFlags": "FUNC_Event | FUNC_Public | FUNC_HasOutParms | FUNC_BlueprintCallable | FUNC_BlueprintEvent"
  },
  {
    "Type": "BlueprintGeneratedClass",
    "Name": "BP_VIPInvitation_Blank_C",
    "Class": "UScriptClass'BlueprintGeneratedClass'",
    "Super": {
      "ObjectName": "BlueprintGeneratedClass'BP_KeycardBase_C'",
      "ObjectPath": "PAYDAY3/Content/Gameplay/Props/KeycardReader/BP_KeycardBase.4"
    },
    "Properties": {
      "SimpleConstructionScript": {
        "ObjectName": "SimpleConstructionScript'BP_VIPInvitation_Blank_C:SimpleConstructionScript_0'",
        "ObjectPath": "PAYDAY3/Content/Prototype/Maps/NightClub/BP_VIPInvitation_Blank.11"
      },
      "InheritableComponentHandler": {
        "ObjectName": "InheritableComponentHandler'BP_VIPInvitation_Blank_C:InheritableComponentHandler'",
        "ObjectPath": "PAYDAY3/Content/Prototype/Maps/NightClub/BP_VIPInvitation_Blank.5"
      }
    },
    "SuperStruct": {
      "ObjectName": "BlueprintGeneratedClass'BP_KeycardBase_C'",
      "ObjectPath": "PAYDAY3/Content/Gameplay/Props/KeycardReader/BP_KeycardBase.4"
    },
    "Children": [
      {
        "ObjectName": "Function'BP_VIPInvitation_Blank_C:GetSensorOutlineComponent'",
        "ObjectPath": "PAYDAY3/Content/Prototype/Maps/NightClub/BP_VIPInvitation_Blank.2"
      },
      {
        "ObjectName": "Function'BP_VIPInvitation_Blank_C:GetSensorComponent'",
        "ObjectPath": "PAYDAY3/Content/Prototype/Maps/NightClub/BP_VIPInvitation_Blank.1"
      },
      {
        "ObjectName": "Function'BP_VIPInvitation_Blank_C:UserConstructionScript'",
        "ObjectPath": "PAYDAY3/Content/Prototype/Maps/NightClub/BP_VIPInvitation_Blank.0"
      }
    ],
    "FuncMap": {
      "UserConstructionScript": {
        "ObjectName": "Function'BP_VIPInvitation_Blank_C:UserConstructionScript'",
        "ObjectPath": "PAYDAY3/Content/Prototype/Maps/NightClub/BP_VIPInvitation_Blank.0"
      },
      "GetSensorComponent": {
        "ObjectName": "Function'BP_VIPInvitation_Blank_C:GetSensorComponent'",
        "ObjectPath": "PAYDAY3/Content/Prototype/Maps/NightClub/BP_VIPInvitation_Blank.1"
      },
      "GetSensorOutlineComponent": {
        "ObjectName": "Function'BP_VIPInvitation_Blank_C:GetSensorOutlineComponent'",
        "ObjectPath": "PAYDAY3/Content/Prototype/Maps/NightClub/BP_VIPInvitation_Blank.2"
      }
    },
    "ClassFlags": "CLASS_Config | CLASS_Optional | CLASS_ReplicationDataIsSetUp | CLASS_CompiledFromBlueprint | CLASS_HasInstancedReference",
    "ClassWithin": {
      "ObjectName": "Class'Object'",
      "ObjectPath": "/Script/CoreUObject"
    },
    "ClassConfigName": "Engine",
    "bCooked": true,
    "ClassDefaultObject": {
      "ObjectName": "BP_VIPInvitation_Blank_C'Default__BP_VIPInvitation_Blank_C'",
      "ObjectPath": "PAYDAY3/Content/Prototype/Maps/NightClub/BP_VIPInvitation_Blank.4"
    }
  },
  {
    "Type": "BP_VIPInvitation_Blank_C",
    "Name": "Default__BP_VIPInvitation_Blank_C",
    "Class": "BlueprintGeneratedClass'PAYDAY3/Content/Prototype/Maps/NightClub/BP_VIPInvitation_Blank.BP_VIPInvitation_Blank_C'",
    "Template": {
      "ObjectName": "BP_KeycardBase_C'Default__BP_KeycardBase_C'",
      "ObjectPath": "PAYDAY3/Content/Gameplay/Props/KeycardReader/BP_KeycardBase.5"
    },
    "Properties": {
      "Interactable": {
        "ObjectName": "SBZInteractableComponent'Default__BP_VIPInvitation_Blank_C:Interaction'",
        "ObjectPath": "PAYDAY3/Content/Prototype/Maps/NightClub/BP_VIPInvitation_Blank.6"
      },
      "RootComponent": {
        "ObjectName": "SceneComponent'Default__BP_VIPInvitation_Blank_C:RootComponent'",
        "ObjectPath": "PAYDAY3/Content/Prototype/Maps/NightClub/BP_VIPInvitation_Blank.9"
      }
    }
  },
  {
    "Type": "InheritableComponentHandler",
    "Name": "InheritableComponentHandler",
    "Outer": "BP_VIPInvitation_Blank_C",
    "Class": "UScriptClass'InheritableComponentHandler'",
    "Properties": {
      "Records": [
        {
          "ComponentClass": {
            "ObjectName": "Class'StaticMeshComponent'",
            "ObjectPath": "/Script/Engine"
          },
          "ComponentTemplate": {
            "ObjectName": "StaticMeshComponent'BP_VIPInvitation_Blank_C:StaticMesh_GEN_VARIABLE'",
            "ObjectPath": "PAYDAY3/Content/Prototype/Maps/NightClub/BP_VIPInvitation_Blank.12"
          },
          "ComponentKey": {
            "OwnerClass": {
              "ObjectName": "BlueprintGeneratedClass'BP_KeycardBase_C'",
              "ObjectPath": "PAYDAY3/Content/Gameplay/Props/KeycardReader/BP_KeycardBase.4"
            },
            "SCSVariableName": "StaticMesh",
            "AssociatedGuid": "F4C552F8-479D569B-E0A8A192-E3701D6C"
          },
          "CookedComponentInstancingData": {
            "ChangedPropertyList": [],
            "bHasValidCookedData": false
          }
        },
        {
          "ComponentClass": {
            "ObjectName": "Class'TextRenderComponent'",
            "ObjectPath": "/Script/Engine"
          },
          "ComponentTemplate": {
            "ObjectName": "TextRenderComponent'BP_VIPInvitation_Blank_C:TextRender_GEN_VARIABLE'",
            "ObjectPath": "PAYDAY3/Content/Prototype/Maps/NightClub/BP_VIPInvitation_Blank.13"
          },
          "ComponentKey": {
            "OwnerClass": {
              "ObjectName": "BlueprintGeneratedClass'BP_KeycardBase_C'",
              "ObjectPath": "PAYDAY3/Content/Gameplay/Props/KeycardReader/BP_KeycardBase.4"
            },
            "SCSVariableName": "TextRender",
            "AssociatedGuid": "F183559C-4DA1D154-5E9B549C-E45244F1"
          },
          "CookedComponentInstancingData": {
            "ChangedPropertyList": [],
            "bHasValidCookedData": false
          }
        },
        {
          "ComponentClass": {
            "ObjectName": "Class'SBZOutlineComponent'",
            "ObjectPath": "/Script/Starbreeze"
          },
          "ComponentTemplate": {
            "ObjectName": "SBZOutlineComponent'BP_VIPInvitation_Blank_C:SBZOutline_GEN_VARIABLE'",
            "ObjectPath": "PAYDAY3/Content/Prototype/Maps/NightClub/BP_VIPInvitation_Blank.7"
          },
          "ComponentKey": {
            "OwnerClass": {
              "ObjectName": "BlueprintGeneratedClass'BP_KeycardBase_C'",
              "ObjectPath": "PAYDAY3/Content/Gameplay/Props/KeycardReader/BP_KeycardBase.4"
            },
            "SCSVariableName": "SBZOutline",
            "AssociatedGuid": "4FE027BE-48EB044B-3692E887-28F67FAD"
          },
          "CookedComponentInstancingData": {
            "ChangedPropertyList": [],
            "bHasValidCookedData": false
          }
        }
      ]
    }
  },
  {
    "Type": "SBZInteractableComponent",
    "Name": "Interaction",
    "Outer": "Default__BP_VIPInvitation_Blank_C",
    "Class": "UScriptClass'SBZInteractableComponent'",
    "Template": {
      "ObjectName": "SBZInteractableComponent'Default__BP_KeycardBase_C:Interaction'",
      "ObjectPath": "PAYDAY3/Content/Gameplay/Props/KeycardReader/BP_KeycardBase.8"
    },
    "Properties": {
      "OnAckCompleteInteraction": {
        "InvocationList": [
          {
            "Object": {
              "ObjectName": "BP_VIPInvitation_Blank_C'Default__BP_VIPInvitation_Blank_C'",
              "ObjectPath": "PAYDAY3/Content/Prototype/Maps/NightClub/BP_VIPInvitation_Blank.4"
            },
            "FunctionName": "HandleAckComplete"
          }
        ]
      },
      "OnServerCompleteInteraction": {
        "InvocationList": [
          {
            "Object": {
              "ObjectName": "BP_VIPInvitation_Blank_C'Default__BP_VIPInvitation_Blank_C'",
              "ObjectPath": "PAYDAY3/Content/Prototype/Maps/NightClub/BP_VIPInvitation_Blank.4"
            },
            "FunctionName": "HandleServerComplete"
          }
        ]
      },
      "NormalDistance": 300.0,
      "PitchDistance": 300.0,
      "ShapeTraceLocationsArray": [
        {
          "ComponentType": {
            "ObjectName": "Class'ActorComponent'",
            "ObjectPath": "/Script/Engine"
          },
          "ComponentName": "Cube"
        }
      ],
      "GameplayEffectsOnInteract": [
        {
          "GameplayEffectClass": {
            "ObjectName": "BlueprintGeneratedClass'GE_VIPInvitation_Template_C'",
            "ObjectPath": "PAYDAY3/Content/Prototype/Maps/NightClub/GE_VIPInvitation_Template.0"
          },
          "Level": 1.0,
          "StackCount": 1
        }
      ],
      "OnFinish3DAudioEvent": {
        "ObjectName": "AkAudioEvent'PLR_INT_Invitation_pickup'",
        "ObjectPath": "PAYDAY3/Content/WwiseAudio/Events/Player/Interactions/Misc/PLR_INT_Invitation_pickup.1"
      },
      "CompletedComment": {
        "ObjectName": "SBZVoiceCommentDataAsset'DA_Voice_Disguise'",
        "ObjectPath": "PAYDAY3/Content/Gameplay/Player/Comments/DA_Voice_Disguise.0"
      }
    }
  },
  {
    "Type": "SBZOutlineComponent",
    "Name": "SBZOutline_GEN_VARIABLE",
    "Outer": "BP_VIPInvitation_Blank_C",
    "Class": "UScriptClass'SBZOutlineComponent'",
    "Template": {
      "ObjectName": "SBZOutlineComponent'BP_KeycardBase_C:SBZOutline_GEN_VARIABLE'",
      "ObjectPath": "PAYDAY3/Content/Gameplay/Props/KeycardReader/BP_KeycardBase.9"
    },
    "Properties": {
      "DefaultAsset": {
        "ObjectName": "SBZOutlineAsset'DA_Interactable_3_5m'",
        "ObjectPath": "PAYDAY3/Content/DataAssets/Outlines/DA_Interactable_3_5m.0"
      }
    }
  },
  {
    "Type": "SceneComponent",
    "Name": "DefaultSceneRoot_GEN_VARIABLE",
    "Outer": "BP_VIPInvitation_Blank_C",
    "Class": "UScriptClass'SceneComponent'"
  },
  {
    "Type": "SceneComponent",
    "Name": "RootComponent",
    "Outer": "Default__BP_VIPInvitation_Blank_C",
    "Class": "UScriptClass'SceneComponent'",
    "Template": {
      "ObjectName": "SceneComponent'Default__BP_KeycardBase_C:RootComponent'",
      "ObjectPath": "PAYDAY3/Content/Gameplay/Props/KeycardReader/BP_KeycardBase.12"
    }
  },
  {
    "Type": "SCS_Node",
    "Name": "SCS_Node_0",
    "Outer": "SimpleConstructionScript_0",
    "Class": "UScriptClass'SCS_Node'",
    "Properties": {
      "ComponentClass": {
        "ObjectName": "Class'SceneComponent'",
        "ObjectPath": "/Script/Engine"
      },
      "ComponentTemplate": {
        "ObjectName": "SceneComponent'BP_VIPInvitation_Blank_C:DefaultSceneRoot_GEN_VARIABLE'",
        "ObjectPath": "PAYDAY3/Content/Prototype/Maps/NightClub/BP_VIPInvitation_Blank.8"
      },
      "VariableGuid": "50FC7034-4A7A2F0E-C4A6C4B5-F5F15188",
      "InternalVariableName": "DefaultSceneRoot"
    }
  },
  {
    "Type": "SimpleConstructionScript",
    "Name": "SimpleConstructionScript_0",
    "Outer": "BP_VIPInvitation_Blank_C",
    "Class": "UScriptClass'SimpleConstructionScript'",
    "Properties": {
      "DefaultSceneRootNode": {
        "ObjectName": "SCS_Node'BP_VIPInvitation_Blank_C:SimpleConstructionScript_0.SCS_Node_0'",
        "ObjectPath": "PAYDAY3/Content/Prototype/Maps/NightClub/BP_VIPInvitation_Blank.10"
      }
    }
  },
  {
    "Type": "StaticMeshComponent",
    "Name": "StaticMesh_GEN_VARIABLE",
    "Outer": "BP_VIPInvitation_Blank_C",
    "Class": "UScriptClass'StaticMeshComponent'",
    "Template": {
      "ObjectName": "StaticMeshComponent'BP_KeycardBase_C:StaticMesh_GEN_VARIABLE'",
      "ObjectPath": "PAYDAY3/Content/Gameplay/Props/KeycardReader/BP_KeycardBase.22"
    },
    "Properties": {
      "StaticMesh": {
        "ObjectName": "StaticMesh'VipCard_01'",
        "ObjectPath": "PAYDAY3/Content/Environment/_Level/NightClub/Prop/VipCard_01/VipCard_01.2"
      },
      "OverrideMaterials": [
        {
          "ObjectName": "MaterialInstanceConstant'MI_VipCard_01'",
          "ObjectPath": "PAYDAY3/Content/Environment/_Level/NightClub/Prop/VipCard_01/Component/MI_VipCard_01.0"
        }
      ],
      "LightmapType": "ELightmapType::ForceVolumetric",
      "BodyInstance": {
        "ObjectType": "ECC_WorldStatic",
        "CollisionEnabled": "ECollisionEnabled::QueryAndPhysics",
        "CollisionProfileName": "BlockAll",
        "CollisionResponses": {
          "ResponseArray": [
            {
              "Channel": "Weapon",
              "Response": "ECR_Block"
            },
            {
              "Channel": "Interaction",
              "Response": "ECR_Block"
            },
            {
              "Channel": "Throwable",
              "Response": "ECR_Block"
            },
            {
              "Channel": "SBZProjectile",
              "Response": "ECR_Block"
            },
            {
              "Channel": "Item",
              "Response": "ECR_Block"
            },
            {
              "Channel": "SBZPiercingThrowable",
              "Response": "ECR_Block"
            }
          ]
        }
      }
    }
  },
  {
    "Type": "TextRenderComponent",
    "Name": "TextRender_GEN_VARIABLE",
    "Outer": "BP_VIPInvitation_Blank_C",
    "Class": "UScriptClass'TextRenderComponent'",
    "Template": {
      "ObjectName": "TextRenderComponent'BP_KeycardBase_C:TextRender_GEN_VARIABLE'",
      "ObjectPath": "PAYDAY3/Content/Gameplay/Props/KeycardReader/BP_KeycardBase.23"
    },
    "Properties": {
      "Text": {
        "CultureInvariantString": null
      },
      "HorizontalAlignment": "EHTA_Center",
      "WorldSize": 18.0,
      "RelativeLocation": {
        "X": 0.17927015,
        "Y": 7.0207744,
        "Z": 0.23742776
      },
      "RelativeRotation": {
        "Pitch": 90.0,
        "Yaw": 90.0,
        "Roll": 0.0
      },
      "bVisible": false
    }
  }
]